surge/__init__.py
surge/_base_client.py
surge/_client.py
surge/_compat.py
surge/_constants.py
surge/_exceptions.py
surge/_files.py
surge/_models.py
surge/_qs.py
surge/_resource.py
surge/_response.py
surge/_streaming.py
surge/_types.py
surge/_version.py
surge/py.typed
surge/_utils/__init__.py
surge/_utils/_compat.py
surge/_utils/_datetime_parse.py
surge/_utils/_logs.py
surge/_utils/_proxy.py
surge/_utils/_reflection.py
surge/_utils/_resources_proxy.py
surge/_utils/_streams.py
surge/_utils/_sync.py
surge/_utils/_transform.py
surge/_utils/_typing.py
surge/_utils/_utils.py
surge/lib/.keep
surge/resources/__init__.py
surge/resources/accounts.py
surge/resources/blasts.py
surge/resources/campaigns.py
surge/resources/contacts.py
surge/resources/messages.py
surge/resources/phone_numbers.py
surge/resources/users.py
surge/resources/verifications.py
surge/resources/webhooks.py
surge/types/__init__.py
surge/types/account.py
surge/types/account_create_params.py
surge/types/account_retrieve_status_params.py
surge/types/account_status.py
surge/types/account_update_params.py
surge/types/blast.py
surge/types/blast_create_params.py
surge/types/call_ended_webhook_event.py
surge/types/campaign.py
surge/types/campaign_approved_webhook_event.py
surge/types/campaign_create_params.py
surge/types/contact.py
surge/types/contact_create_params.py
surge/types/contact_opted_in_webhook_event.py
surge/types/contact_opted_out_webhook_event.py
surge/types/contact_update_params.py
surge/types/conversation_created_webhook_event.py
surge/types/message.py
surge/types/message_create_params.py
surge/types/message_delivered_webhook_event.py
surge/types/message_failed_webhook_event.py
surge/types/message_received_webhook_event.py
surge/types/message_sent_webhook_event.py
surge/types/organization.py
surge/types/phone_number.py
surge/types/phone_number_purchase_params.py
surge/types/unwrap_webhook_event.py
surge/types/user.py
surge/types/user_create_params.py
surge/types/user_create_token_params.py
surge_sdk-0.4.0.dist-info/METADATA
surge_sdk-0.4.0.dist-info/WHEEL
surge_sdk-0.4.0.dist-info/licenses/LICENSE
surge_sdk-0.4.0.dist-info/RECORD
